insights_net/__init__.py
insights_net/client.py
insights_net/main.py
insights_net/commands/__init__.py
insights_net/commands/host.py
insights_net/commands/info.py
insights_net/commands/net.py
insights_net/commands/ovn.py
insights_net/commands/printing.py
insights_net/plugins/__init__.py
insights_net/plugins/commands.py
insights_net/plugins/datasources.py
insights_net/plugins/combiners/__init__.py
insights_net/plugins/combiners/find_ip.py
insights_net/plugins/combiners/ovn.py
insights_net/plugins/combiners/ovs.py
insights_net/plugins/facts/__init__.py
insights_net/plugins/facts/host_info.py
insights_net/plugins/parsers/__init__.py
insights_net/plugins/parsers/ip.py
insights_net/plugins/parsers/ocp.py
insights_net/plugins/parsers/ocp_net.py
insights_net/plugins/parsers/ofp_actions.py
insights_net/plugins/parsers/ovn.py
insights_net/plugins/parsers/ovs.py
insights_net/plugins/parsers/ovsdb.py
insights_net-0.0.2.data/scripts/insights-net
insights_net-0.0.2.dist-info/METADATA
insights_net-0.0.2.dist-info/WHEEL
insights_net-0.0.2.dist-info/top_level.txt
insights_net-0.0.2.dist-info/RECORD
