Metadata-Version: 2.1
Name: insights-net
Version: 0.0.2
Summary: Network analysis tools based on insights-core
Home-page: UNKNOWN
Author: Adrián Moreno
Author-email: amorenoz@redhat.com
License: Apache Software License 2.0
Platform: UNKNOWN
Classifier: Development Status :: 2 - Pre-Alpha
Classifier: Intended Audience :: Developers
Classifier: License :: OSI Approved :: Apache Software License
Classifier: Natural Language :: English
Classifier: Programming Language :: Python :: 3
Classifier: Programming Language :: Python :: 3.4
Classifier: Programming Language :: Python :: 3.5
Classifier: Programming Language :: Python :: 3.6
Requires-Dist: ipython
Requires-Dist: coverage
Requires-Dist: ipykernel
Requires-Dist: click
Requires-Dist: colorama
Requires-Dist: rich
Requires-Dist: ovsdbapp
Requires-Dist: insights-core
Requires-Dist: ovs-dbg (>=0.0.10)
